eplus_gym/__init__.py
eplus_gym/agents/__init__.py
eplus_gym/agents/ddqn_bilstm/BiLSTM_model.py
eplus_gym/agents/ddqn_bilstm/deep_q_network.py
eplus_gym/agents/ddqn_bilstm/dqn_agent.py
eplus_gym/agents/ddqn_bilstm/replay_memory.py
eplus_gym/agents/ddqn_mlp/deep_q_network.py
eplus_gym/agents/ddqn_mlp/dqn_agent.py
eplus_gym/agents/ddqn_mlp/main_dqn.py
eplus_gym/agents/ddqn_mlp/replay_memory.py
eplus_gym/agents/q_transformer/__init__.py
eplus_gym/agents/q_transformer/deep_q_network.py
eplus_gym/agents/q_transformer/dqn_agent.py
eplus_gym/agents/q_transformer/positional_encoding.py
eplus_gym/agents/q_transformer/replay_memory.py
eplus_gym/agents/q_transformer/transformer_model.py
eplus_gym/envs/__init__.py
eplus_gym/envs/energyplus.py
eplus_gym/envs/env.py
eplus_gym/envs/utils.py
eplus_gym/envs/assets/AUS_WA_Perth.Metro.946080_TMYx.2007-2021.epw
eplus_gym/envs/assets/FRA_BT_Brest.Bretagne.AP.071100_TMYx.2009-2023.epw
eplus_gym/envs/assets/LUX_LU_Luxembourg.AP.065900_TMYx.2004-2018.epw
eplus_gym/envs/assets/Luxembourg.csv
eplus_gym/envs/assets/PRT_LB_Lisboa.Portela.AP.085360_TMYx.2007-2021.epw
eplus_gym/envs/assets/USA.csv
eplus_gym/envs/assets/USA_SD_Rapid.City.Rgnl.AP.726620_TMYx.2007-2021.epw
eplus_gym/envs/assets/ZAF_WC_Cape.Town.Portnet.688170_TMYx.2009-2023.epw
eplus_gym/envs/assets/__init__.py
eplus_gym/envs/assets/africa.csv
eplus_gym/envs/assets/australia.csv
eplus_gym/envs/assets/brest.csv
eplus_gym/envs/assets/model.csv
eplus_gym/envs/assets/model.idf
eplus_gym/envs/assets/modelMeter.csv
eplus_gym/envs/assets/modelSsz.csv
eplus_gym/envs/assets/modelZsz.csv
eplus_gym/envs/assets/portugal.csv
eplus_gym/envs/assets/normalization/DDQN_BiLSTM.csv
eplus_gym/envs/assets/normalization/DDQN_MLP.csv
eplus_gym/envs/assets/normalization/Q-transformer.csv
eplus_gym_khalil-0.1.1.dist-info/licenses/LICENSE
eplus_gym_khalil-0.1.1.dist-info/METADATA
eplus_gym_khalil-0.1.1.dist-info/WHEEL
eplus_gym_khalil-0.1.1.dist-info/top_level.txt
eplus_gym_khalil-0.1.1.dist-info/RECORD
