Metadata-Version: 2.4
Name: eplus-gym-khalil
Version: 0.1.1
Summary: EnergyPlus environments for Gymnasium
Author-email: Khalil Al Sayed <khalil.alsayed198@gmail.com>
Project-URL: Homepage, https://github.com/khalilalsayed/energyplus-gym
Project-URL: Repository, https://github.com/khalilalsayed/energyplus-gym
Project-URL: Issues, https://github.com/khalilalsayed/energyplus-gym/issues
Keywords: EnergyPlus,Gymnasium,RL,HVAC,BEMS
Classifier: Development Status :: 3 - Alpha
Classifier: Intended Audience :: Science/Research
Classifier: Topic :: Scientific/Engineering
Classifier: License :: OSI Approved :: MIT License
Classifier: Programming Language :: Python :: 3
Classifier: Programming Language :: Python :: 3.10
Classifier: Programming Language :: Python :: 3.11
Classifier: Programming Language :: Python :: 3.12
Requires-Python: >=3.10
License-File: LICENSE
Requires-Dist: gymnasium<1.0,>=0.28
Requires-Dist: numpy<2.0,>=1.23
Requires-Dist: pandas<3.0,>=1.5
Provides-Extra: examples
Requires-Dist: matplotlib>=3.5; extra == "examples"
Requires-Dist: torch>=2.0; extra == "examples"
Requires-Dist: scikit-learn>=1.3; extra == "examples"
Dynamic: license-file
